torch_l1_snr/__init__.py
torch_l1_snr/l1snr.py
torch_l1_snr-0.1.1.dist-info/licenses/LICENSE
torch_l1_snr-0.1.1.dist-info/METADATA
torch_l1_snr-0.1.1.dist-info/WHEEL
torch_l1_snr-0.1.1.dist-info/top_level.txt
torch_l1_snr-0.1.1.dist-info/RECORD
