Metadata-Version: 2.4
Name: torch-l1-snr
Version: 0.1.1
Summary: L1-SNR loss functions for audio source separation in PyTorch
Home-page: https://github.com/crlandsc/torch-l1-snr
Author: Christopher Landschoot
Author-email: crlandschoot@gmail.com
License: MIT
Classifier: Intended Audience :: Developers
Classifier: Intended Audience :: Science/Research
Classifier: License :: OSI Approved :: MIT License
Classifier: Programming Language :: Python :: 3
Classifier: Programming Language :: Python :: 3.8
Classifier: Programming Language :: Python :: 3.9
Classifier: Programming Language :: Python :: 3.10
Classifier: Programming Language :: Python :: 3.11
Classifier: Programming Language :: Python :: 3.12
Classifier: Operating System :: OS Independent
Classifier: Topic :: Scientific/Engineering :: Artificial Intelligence
Classifier: Topic :: Multimedia :: Sound/Audio :: Analysis
Requires-Python: >=3.8
License-File: LICENSE
Requires-Dist: torch
Requires-Dist: torchaudio
Requires-Dist: numpy>=1.21.0
Dynamic: license-file
